reinvent_hitl_scoring/__init__.py
reinvent_hitl_scoring/configs/__init__.py
reinvent_hitl_scoring/configs/config.py
reinvent_hitl_scoring/configs/test_config.json
reinvent_hitl_scoring/scoring/__init__.py
reinvent_hitl_scoring/scoring/component_parameters.py
reinvent_hitl_scoring/scoring/score_summary.py
reinvent_hitl_scoring/scoring/score_transformations.py
reinvent_hitl_scoring/scoring/scoring_function_factory.py
reinvent_hitl_scoring/scoring/scoring_function_parameters.py
reinvent_hitl_scoring/scoring/utils.py
reinvent_hitl_scoring/scoring/diversity_filters/__init__.py
reinvent_hitl_scoring/scoring/diversity_filters/curriculum_learning/__init__.py
reinvent_hitl_scoring/scoring/diversity_filters/curriculum_learning/base_diversity_filter.py
reinvent_hitl_scoring/scoring/diversity_filters/curriculum_learning/column_names_enum.py
reinvent_hitl_scoring/scoring/diversity_filters/curriculum_learning/diversity_filter.py
reinvent_hitl_scoring/scoring/diversity_filters/curriculum_learning/diversity_filter_memory.py
reinvent_hitl_scoring/scoring/diversity_filters/curriculum_learning/diversity_filter_parameters.py
reinvent_hitl_scoring/scoring/diversity_filters/curriculum_learning/identical_murcko_scaffold.py
reinvent_hitl_scoring/scoring/diversity_filters/curriculum_learning/identical_topological_scaffold.py
reinvent_hitl_scoring/scoring/diversity_filters/curriculum_learning/loggable_data_dto.py
reinvent_hitl_scoring/scoring/diversity_filters/curriculum_learning/memory_record_dto.py
reinvent_hitl_scoring/scoring/diversity_filters/curriculum_learning/no_filter.py
reinvent_hitl_scoring/scoring/diversity_filters/curriculum_learning/no_filter_with_penalty.py
reinvent_hitl_scoring/scoring/diversity_filters/curriculum_learning/scaffold_similarity.py
reinvent_hitl_scoring/scoring/diversity_filters/curriculum_learning/update_diversity_filter_dto.py
reinvent_hitl_scoring/scoring/diversity_filters/lib_invent/__init__.py
reinvent_hitl_scoring-0.0.18.dist-info/LICENSE
reinvent_hitl_scoring-0.0.18.dist-info/METADATA
reinvent_hitl_scoring-0.0.18.dist-info/WHEEL
reinvent_hitl_scoring-0.0.18.dist-info/top_level.txt
reinvent_hitl_scoring-0.0.18.dist-info/RECORD
