Metadata-Version: 2.1
Name: reinvent-hitl-scoring
Version: 0.0.18
Summary: Scoring functions for Reinvent adapted to the HITL_AL_GOMG workflow
Home-page: https://github.com/yasminenahal/reinvent-hitl-scoring.git
Author: Yasmine Nahal
Author-email: yasminenahal@aalto.fi
License: UNKNOWN
Platform: UNKNOWN
Classifier: Programming Language :: Python :: 3
Classifier: License :: OSI Approved :: MIT License
Classifier: Operating System :: OS Independent
Requires-Python: >=3.7
